Workbook

Sheet Basketball Game Sales
A1: Date | B1: Item | C1: Category | D1: Price | E1: Profit | F1: Actual Profit | G1: Calories
A2: 43466 | B2: Beer | C2: Beverages | D2: 4 | E2: 0.5 | F2: 2 | G2: =VLOOKUP(B2,Calories!$A$1:$B$15,2,FALSE) -> 200
A3: 43466 | B3: Hamburger | C3: Hot Food | D3: 3 | E3: 0.66666667 | F3: 2 | G3: =VLOOKUP(B3,Calories!$A$1:$B$15,2,FALSE) -> 320
A4: 43466 | B4: Popcorn | C4: Hot Food | D4: 5 | E4: 0.8 | F4: 4 | G4: =VLOOKUP(B4,Calories!$A$1:$B$15,2,FALSE) -> 500
A5: 43466 | B5: Pizza | C5: Hot Food | D5: 2 | E5: 0.25 | F5: 0.5 | G5: =VLOOKUP(B5,Calories!$A$1:$B$15,2,FALSE) -> 480
A6: 43466 | B6: Bottled Water | C6: Beverages | D6: 3 | E6: 0.83333333 | F6: 2.5 | G6: =VLOOKUP(B6,Calories!$A$1:$B$15,2,FALSE) -> 0
A7: 43466 | B7: Hot Dog | C7: Hot Food | D7: 1.5 | E7: 0.66666667 | F7: 1 | G7: =VLOOKUP(B7,Calories!$A$1:$B$15,2,FALSE) -> 265
A8: 43466 | B8: Chocolate Dipped Cone | C8: Frozen Treats | D8: 3 | E8: 0.5 | F8: 1.5 | G8: =VLOOKUP(B8,Calories!$A$1:$B$15,2,FALSE) -> 300
A9: 43467 | B9: Soda | C9: Beverages | D9: 2.5 | E9: 0.8 | F9: 2 | G9: =VLOOKUP(B9,Calories!$A$1:$B$15,2,FALSE) -> 120
A10: 43467 | B10: Chocolate Bar | C10: Candy | D10: 2 | E10: 0.75 | F10: 1.5 | G10: =VLOOKUP(B10,Calories!$A$1:$B$15,2,FALSE) -> 255
A11: 43467 | B11: Hamburger | C11: Hot Food | D11: 3 | E11: 0.66666667 | F11: 2 | G11: =VLOOKUP(B11,Calories!$A$1:$B$15,2,FALSE) -> 320
A12: 43467 | B12: Beer | C12: Beverages | D12: 4 | E12: 0.5 | F12: 2 | G12: =VLOOKUP(B12,Calories!$A$1:$B$15,2,FALSE) -> 200
A13: 43467 | B13: Hot Dog | C13: Hot Food | D13: 1.5 | E13: 0.66666667 | F13: 1 | G13: =VLOOKUP(B13,Calories!$A$1:$B$15,2,FALSE) -> 265
... A200: 43504 | B200: Popsicle | C200: Frozen Treats | D200: 3 | E200: 0.83333333 | F200: 2.5 | G200: =VLOOKUP(B200,Calories!$A$1:$B$15,2,FALSE) -> 150

Sheet Calories
A1: Item | B1: Calories
A2: Beer | B2: 200
A3: Bottled Water | B3: 0
A4: Chocolate Bar | B4: 255
A5: Chocolate Dipped Cone | B5: 300
A6: Gummy Bears | B6: 300
A7: Hamburger | B7: 320
A8: Hot Dog | B8: 265
A9: Ice Cream Sandwich | B9: 240
A10: Licorice Rope | B10: 280
A11: Nachos | B11: 560
A12: Pizza | B12: 480
A13: Popcorn | B13: 500
... A15: Soda | B15: 120
A18: Match | B18: =MATCH("Hamburger",A2:A15,0) -> 6
A19: Index | B19: =INDEX(A1:B15,3,2) -> 0
A20: Offset | B20: =OFFSET(A1,3,0) -> Chocolate Bar
A21: Small | B21: =SMALL(B2:B15,3) -> 150

Sheet Pivot
A3: Sum of Price
A4: Row Labels | B4: Total
A5: Beer | B5: 80
A6: Bottled Water | B6: 39
A7: Chocolate Bar | B7: 26
A8: Chocolate Dipped Cone | B8: 33
A9: Gummy Bears | B9: 28
A10: Hamburger | B10: 48
A11: Hot Dog | B11: 22.5
A12: Ice Cream Sandwich | B12: 30
A13: Licorice Rope | B13: 26
A14: Nachos | B14: 45
A15: Pizza | B15: 34
A16: Popcorn | B16: 80
... A19: Grand Total | B19: 563

Sheet Fee Schedule
A1: Item | B1: Beer | C1: Bottled Water | D1: Chocolate Bar | E1: Chocolate Dipped Cone | F1: Gummy Bears | G1: Hamburger | H1: Hot Dog | I1: Ice Cream Sandwich | J1: Licorice Rope | K1: Nachos | L1: Pizza | M1: Popcorn | N1: Popsicle | O1: Soda
A2: Percent | B2: 0.15 | C2: 0.05 | D2: 0.15 | E2: 0.15 | F2: 0.15 | G2: 0.05 | H2: 0.05 | I2: 0.15 | J2: 0.15 | K2: 0.05 | L2: 0.05 | M2: 0.05 | N2: 0.15 | O2: 0.15

Sheet Revenue By Item
A1: Row Labels | B1: Sum of Price | D1: Total Cut for Coach:
A2: Beer | B2: 80 | D2: {=SUMPRODUCT(B2:B15,TRANSPOSE('Fee Schedule'!B2:O2))} -> 57.6
A3: Bottled Water | B3: 39
A4: Chocolate Bar | B4: 26
A5: Chocolate Dipped Cone | B5: 33
A6: Gummy Bears | B6: 28
A7: Hamburger | B7: 48
A8: Hot Dog | B8: 22.5
A9: Ice Cream Sandwich | B9: 30
A10: Licorice Rope | B10: 26
A11: Nachos | B11: 45
A12: Pizza | B12: 34
A13: Popcorn | B13: 80
A14: Popsicle | B14: 39
A15: Soda | B15: 32.5

Sheet Calories-Solver
A1: Item | B1: Calories | C1: How many?
A2: Beer | B2: 200 | C2: 0
A3: Bottled Water | B3: 0 | C3: 0
A4: Chocolate Bar | B4: 255 | C4: 0
A5: Chocolate Dipped Cone | B5: 300 | C5: 0
A6: Gummy Bears | B6: 300 | C6: 0
A7: Hamburger | B7: 320 | C7: 0
A8: Hot Dog | B8: 265 | C8: 0
A9: Ice Cream Sandwich | B9: 240 | C9: 0
A10: Licorice Rope | B10: 280 | C10: 1
A11: Nachos | B11: 560 | C11: 2
A12: Pizza | B12: 480 | C12: 0
A13: Popcorn | B13: 500 | C13: 2
... A15: Soda | B15: 120 | C15: 0
B16: Total Items: | C16: =SUM(C2:C15) -> 5
B17: Total Calories: | C17: =SUMPRODUCT(B2:B15,C2:C15) -> 2400
